src/alu_4bit.v
module alu_4bit(
    input  [3:0] A,
    input  [3:0] B,
    input  [2:0] sel,
    output reg [3:0] Y,
    output reg carry_out,
    output reg zero,
    output reg negative,
    output reg overflow
);

    reg [4:0] temp;

    always @(*) begin
        Y = 4'b0000;
        carry_out = 0;
        zero = 0;
        negative = 0;
        overflow = 0;
        temp = 5'b00000;

        case (sel)

            3'b000: begin
                temp = A + B;
                Y = temp[3:0];
                carry_out = temp[4];
                overflow = (~A[3] & ~B[3] & Y[3]) | (A[3] & B[3] & ~Y[3]);
            end

            3'b001: begin
                temp = A - B;
                Y = temp[3:0];
                carry_out = temp[4];
                overflow = (~A[3] & B[3] & Y[3]) | (A[3] & ~B[3] & ~Y[3]);
            end

            3'b010: begin
                Y = A & B;
            end

            3'b011: begin
                Y = A | B;
            end

            3'b100: begin
                Y = A ^ B;
            end

            3'b101: begin
                Y = ~A;
            end

            3'b110: begin
                Y = A << 1;
            end

            3'b111: begin
                Y = A >> 1;
            end

            default: begin
                Y = 4'b0000;
            end

        endcase

        if (Y == 4'b0000)
            zero = 1;
        else
            zero = 0;

        negative = Y[3];

    end

endmodule

tb/alu_4bit_tb.v
`timescale 1ns/1ps

module alu_4bit_tb;

    reg [3:0] A;
    reg [3:0] B;
    reg [2:0] sel;

    wire [3:0] Y;
    wire carry_out;
    wire zero;
    wire negative;
    wire overflow;

    integer test_count;
    integer pass_count;
    integer fail_count;

    alu_4bit uut (
        .A(A),
        .B(B),
        .sel(sel),
        .Y(Y),
        .carry_out(carry_out),
        .zero(zero),
        .negative(negative),
        .overflow(overflow)
    );

    task check_result;
        input [3:0] expected_Y;
        input expected_zero;
        input expected_negative;
        input expected_overflow;
        input [80*8:1] test_name;

        begin
            test_count = test_count + 1;
            #1;

            if (
                Y === expected_Y &&
                zero === expected_zero &&
                negative === expected_negative &&
                overflow === expected_overflow
            ) begin
                pass_count = pass_count + 1;
                $display("PASS: %s | A=%d B=%d sel=%b Y=%d zero=%b negative=%b overflow=%b",
                         test_name, A, B, sel, Y, zero, negative, overflow);
            end else begin
                fail_count = fail_count + 1;
                $display("FAIL: %s | A=%d B=%d sel=%b", test_name, A, B, sel);
                $display("      Expected: Y=%d zero=%b negative=%b overflow=%b",
                         expected_Y, expected_zero, expected_negative, expected_overflow);
                $display("      Got:      Y=%d zero=%b negative=%b overflow=%b",
                         Y, zero, negative, overflow);
            end
        end
    endtask

    initial begin
        $dumpfile("waveforms/alu_4bit.vcd");
        $dumpvars(0, alu_4bit_tb);

        test_count = 0;
        pass_count = 0;
        fail_count = 0;

        $display("Starting Self-Checking 4-bit ALU Testbench");
        $display("------------------------------------------------");

        // Main test case: A = 5, B = 3
        A = 4'd5;
        B = 4'd3;

        sel = 3'b000; #10;
        check_result(4'd8, 0, 1, 1, "ADD 5 + 3");

        sel = 3'b001; #10;
        check_result(4'd2, 0, 0, 0, "SUB 5 - 3");

        sel = 3'b010; #10;
        check_result(4'd1, 0, 0, 0, "AND 5 & 3");

        sel = 3'b011; #10;
        check_result(4'd7, 0, 0, 0, "OR 5 | 3");

        sel = 3'b100; #10;
        check_result(4'd6, 0, 0, 0, "XOR 5 ^ 3");

        sel = 3'b101; #10;
        check_result(4'd10, 0, 1, 0, "NOT 5");

        sel = 3'b110; #10;
        check_result(4'd10, 0, 1, 0, "SHIFT LEFT 5");

        sel = 3'b111; #10;
        check_result(4'd2, 0, 0, 0, "SHIFT RIGHT 5");

        // Zero flag test
        A = 4'd3;
        B = 4'd3;
        sel = 3'b001; #10;
        check_result(4'd0, 1, 0, 0, "ZERO TEST 3 - 3");

        // Carry test: 15 + 1 = 16, lower 4 bits = 0, carry = 1
        A = 4'd15;
        B = 4'd1;
        sel = 3'b000; #10;
        check_result(4'd0, 1, 0, 0, "CARRY TEST 15 + 1");

        // Signed overflow test: 7 + 1 = 8
        // In 4-bit signed numbers, 7 + 1 overflows to -8
        A = 4'd7;
        B = 4'd1;
        sel = 3'b000; #10;
        check_result(4'd8, 0, 1, 1, "SIGNED OVERFLOW TEST 7 + 1");

        // Negative flag test
        A = 4'd8;
        B = 4'd1;
        sel = 3'b010; #10;
        check_result(4'd0, 1, 0, 0, "AND 8 & 1");

        A = 4'd8;
        B = 4'd1;
        sel = 3'b011; #10;
        check_result(4'd9, 0, 1, 0, "NEGATIVE FLAG TEST 8 | 1");

        $display("------------------------------------------------");
        $display("Testbench completed");
        $display("Total tests: %0d", test_count);
        $display("Passed:      %0d", pass_count);
        $display("Failed:      %0d", fail_count);

        if (fail_count == 0)
            $display("ALL TESTS PASSED");
        else
            $display("SOME TESTS FAILED");

        $finish;
    end

endmodule

waveforms/alu_4bit.vcd
$date
	Mon Jun 22 14:24:16 2026
$end
$version
	Icarus Verilog
$end
$timescale
	1ps
$end
$scope module alu_4bit_tb $end
$var wire 1 ! zero $end
$var wire 1 " overflow $end
$var wire 1 # negative $end
$var wire 1 $ carry_out $end
$var wire 4 % Y [3:0] $end
$var reg 4 & A [3:0] $end
$var reg 4 ' B [3:0] $end
$var reg 3 ( sel [2:0] $end
$var integer 32 ) fail_count [31:0] $end
$var integer 32 * pass_count [31:0] $end
$var integer 32 + test_count [31:0] $end
$scope module uut $end
$var wire 4 , A [3:0] $end
$var wire 4 - B [3:0] $end
$var wire 3 . sel [2:0] $end
$var reg 4 / Y [3:0] $end
$var reg 1 $ carry_out $end
$var reg 1 # negative $end
$var reg 1 " overflow $end
$var reg 5 0 temp [4:0] $end
$var reg 1 ! zero $end
$upscope $end
$scope task check_result $end
$var reg 4 1 expected_Y [3:0] $end
$var reg 1 2 expected_negative $end
$var reg 1 3 expected_overflow $end
$var reg 1 4 expected_zero $end
$var reg 640 5 test_name [640:1] $end
$upscope $end
$upscope $end
$enddefinitions $end
$comment Show the parameter values. $end
$dumpall
$end
#0
$dumpvars
bx 5
x4
x3
x2
bx 1
b1000 0
b1000 /
b0 .
b11 -
b101 ,
b0 +
b0 *
b0 )
b0 (
b11 '
b101 &
b1000 %
0$
1#
1"
0!
$end
#10000
b1 +
b10000010100010001000100001000000011010100100000001010110010000000110011 5
13
12
04
b1000 1
#11000
b10 0
0"
0#
b10 %
b10 /
b1 (
b1 .
b1 *
#21000
b10 +
b10100110101010101000010001000000011010100100000001011010010000000110011 5
03
02
b10 1
#22000
b0 0
b1 %
b1 /
b10 (
b10 .
b10 *
#32000
b11 +
b10000010100111001000100001000000011010100100000001001100010000000110011 5
b1 1
#33000
b111 %
b111 /
b11 (
b11 .
b11 *
#43000
b100 +
b100111101010010001000000011010100100000011111000010000000110011 5
b111 1
#44000
b110 %
b110 /
b100 (
b100 .
b100 *
#54000
b101 +
b10110000100111101010010001000000011010100100000010111100010000000110011 5
b110 1
#55000
1#
b1010 %
b1010 /
b101 (
b101 .
b101 *
#65000
b110 +
b100111001001111010101000010000000110101 5
12
b1010 1
#66000
1#
b1010 %
b1010 /
b110 (
b110 .
b110 *
#76000
b111 +
b10100110100100001001001010001100101010000100000010011000100010101000110010101000010000000110101 5
#77000
0#
b10 %
b10 /
b111 (
b111 .
b111 *
#87000
b1000 +
b1010011010010000100100101000110010101000010000001010010010010010100011101001000010101000010000000110101 5
02
b10 1
#88000
1!
b0 %
b0 /
b1 (
b1 .
b11 &
b11 ,
b1000 *
#98000
b1001 +
b10110100100010101010010010011110010000001010100010001010101001101010100001000000011001100100000001011010010000000110011 5
14
b0 1
#99000
1$
b10000 0
1!
b0 (
b0 .
b1 '
b1 -
b1111 &
b1111 ,
b1001 *
#109000
b1010 +
b100001101000001010100100101001001011001001000000101010001000101010100110101010000100000001100010011010100100000001010110010000000110001 5
#110000
1#
1"
b1000 %
b1000 /
b1000 0
0!
0$
b111 &
b111 ,
b1010 *
#120000
b1011 +
b101001101001001010001110100111001000101010001000010000001001111010101100100010101010010010001100100110001001111010101110010000001010100010001010101001101010100001000000011011100100000001010110010000000110001 5
13
12
04
b1000 1
#121000
1!
b0 0
0"
0#
b0 %
b0 /
b10 (
b10 .
b1000 &
b1000 ,
b1011 *
#131000
b1100 +
b10000010100111001000100001000000011100000100000001001100010000000110001 5
03
02
14
b0 1
#132000
1#
b1001 %
b1001 /
0!
b11 (
b11 .
b1100 *
#142000
b1101 +
b10011100100010101000111010000010101010001001001010101100100010100100000010001100100110001000001010001110010000001010100010001010101001101010100001000000011100000100000011111000010000000110001 5
12
04
b1001 1
#143000
b1101 *
