vlsi-4bit-alu/src/alu_4bit.v
module alu_4bit(
    input  [3:0] A,
    input  [3:0] B,
    input  [2:0] sel,
    output reg [3:0] Y,
    output reg carry_out,
    output reg zero
);

    reg [4:0] temp;

    always @(*) begin
        carry_out = 0;
        temp = 5'b00000;

        case (sel)
            3'b000: begin
                temp = A + B;
                Y = temp[3:0];
                carry_out = temp[4];
            end

            3'b001: begin
                temp = A - B;
                Y = temp[3:0];
                carry_out = temp[4];
            end

            3'b010: begin
                Y = A & B;
            end

            3'b011: begin
                Y = A | B;
            end

            3'b100: begin
                Y = A ^ B;
            end

            3'b101: begin
                Y = ~A;
            end

            3'b110: begin
                Y = A << 1;
            end

            3'b111: begin
                Y = A >> 1;
            end

            default: begin
                Y = 4'b0000;
            end
        endcase

        if (Y == 4'b0000)
            zero = 1;
        else
            zero = 0;
    end

endmodule

vlsi-4bit-alu/tb/alu_4bit_tb.v
`timescale 1ns/1ps

module alu_4bit_tb;

    reg [3:0] A;
    reg [3:0] B;
    reg [2:0] sel;

    wire [3:0] Y;
    wire carry_out;
    wire zero;

    alu_4bit uut (
        .A(A),
        .B(B),
        .sel(sel),
        .Y(Y),
        .carry_out(carry_out),
        .zero(zero)
    );

    initial begin
        $dumpfile("waveforms/alu_4bit.vcd");
        $dumpvars(0, alu_4bit_tb);

        $display("Starting 4-bit ALU Testbench");
        $display("--------------------------------");

        A = 4'b0101;
        B = 4'b0011;

        sel = 3'b000; #10;
        $display("ADD: A=%b B=%b Y=%b carry=%b zero=%b", A, B, Y, carry_out, zero);

        sel = 3'b001; #10;
        $display("SUB: A=%b B=%b Y=%b carry=%b zero=%b", A, B, Y, carry_out, zero);

        sel = 3'b010; #10;
        $display("AND: A=%b B=%b Y=%b carry=%b zero=%b", A, B, Y, carry_out, zero);

        sel = 3'b011; #10;
        $display("OR : A=%b B=%b Y=%b carry=%b zero=%b", A, B, Y, carry_out, zero);

        sel = 3'b100; #10;
        $display("XOR: A=%b B=%b Y=%b carry=%b zero=%b", A, B, Y, carry_out, zero);

        sel = 3'b101; #10;
        $display("NOT: A=%b B=%b Y=%b carry=%b zero=%b", A, B, Y, carry_out, zero);

        sel = 3'b110; #10;
        $display("SHL: A=%b B=%b Y=%b carry=%b zero=%b", A, B, Y, carry_out, zero);

        sel = 3'b111; #10;
        $display("SHR: A=%b B=%b Y=%b carry=%b zero=%b", A, B, Y, carry_out, zero);

        A = 4'b0011;
        B = 4'b0011;
        sel = 3'b001; #10;
        $display("ZERO TEST: A=%b B=%b Y=%b carry=%b zero=%b", A, B, Y, carry_out, zero);

        $display("--------------------------------");
        $display("Testbench completed");

        $finish;
    end

endmodule

vlsi-4bit-alu/waveforms/alu_4bit.vcd
$date
	Mon Jun 22 13:33:22 2026
$end
$version
	Icarus Verilog
$end
$timescale
	1ps
$end
$scope module alu_4bit_tb $end
$var wire 1 ! zero $end
$var wire 1 " carry_out $end
$var wire 4 # Y [3:0] $end
$var reg 4 $ A [3:0] $end
$var reg 4 % B [3:0] $end
$var reg 3 & sel [2:0] $end
$scope module uut $end
$var wire 4 ' A [3:0] $end
$var wire 4 ( B [3:0] $end
$var wire 3 ) sel [2:0] $end
$var reg 4 * Y [3:0] $end
$var reg 1 " carry_out $end
$var reg 5 + temp [4:0] $end
$var reg 1 ! zero $end
$upscope $end
$upscope $end
$enddefinitions $end
$comment Show the parameter values. $end
$dumpall
$end
#0
$dumpvars
b1000 +
b1000 *
b0 )
b11 (
b101 '
b0 &
b11 %
b101 $
b1000 #
0"
0!
$end
#10000
b10 #
b10 *
b10 +
b1 &
b1 )
#20000
b1 #
b1 *
b0 +
b10 &
b10 )
#30000
b111 #
b111 *
b11 &
b11 )
#40000
b110 #
b110 *
b100 &
b100 )
#50000
b1010 #
b1010 *
b101 &
b101 )
#60000
b110 &
b110 )
#70000
b10 #
b10 *
b111 &
b111 )
#80000
1!
b0 #
b0 *
b1 &
b1 )
b11 $
b11 '
